pymot/__init__.py
pymot/mot.py
pymot/utils.py
pymot/object_detection/__init__.py
pymot/object_detection/yolo.py
pymot/tracking/__init__.py
pymot/tracking/deep_sort/__init__.py
pymot/tracking/deep_sort/ckpt.t7
pymot/tracking/deep_sort/detection.py
pymot/tracking/deep_sort/iou_matching.py
pymot/tracking/deep_sort/kalman_filter.py
pymot/tracking/deep_sort/linear_assignment.py
pymot/tracking/deep_sort/nn_matching.py
pymot/tracking/deep_sort/pytorch_reid_feature_extractor.py
pymot/tracking/deep_sort/track.py
pymot/tracking/deep_sort/tracker.py
pymot-0.0.5.dist-info/LICENSE
pymot-0.0.5.dist-info/WHEEL
pymot-0.0.5.dist-info/METADATA
pymot-0.0.5.dist-info/RECORD
