Metadata-Version: 2.1
Name: pymot
Version: 0.0.5
Summary: Multi object tracking
Author-email: Simas Sirutavicius <sirutavicius.simas@gmail.com>
Requires-Python: >=3.8
Classifier: License :: OSI Approved :: MIT License
Classifier: Programming Language :: Python :: 3
Requires-Dist: numpy ==1.24.3
Requires-Dist: opencv-python ==4.7.0.72
Requires-Dist: scipy ==1.10.1
Requires-Dist: torch ==2.0.1
Requires-Dist: torchvision ==0.15.2
Project-URL: Source, https://github.com/simsiru/pymot
